dremio/__init__.py
dremio/dremio.py
dremio/exceptions.py
dremio/version.py
dremio/_mixins/__init__.py
dremio/_mixins/_catalog.py
dremio/_mixins/_dataset.py
dremio/_mixins/_flight.py
dremio/_mixins/_folder.py
dremio/_mixins/_query.py
dremio/_mixins/_reflection.py
dremio/_mixins/_role.py
dremio/_mixins/_sql.py
dremio/_mixins/_table.py
dremio/_mixins/_user.py
dremio/_mixins/baseclass.py
dremio/models/__init__.py
dremio/models/accesscontrol.py
dremio/models/backup.py
dremio/models/baseclasses.py
dremio/models/custom_objects.py
dremio/models/dataset.py
dremio/models/dremio_objects.py
dremio/models/dremio_utils.py
dremio/models/flight_config.py
dremio/models/folder.py
dremio/models/inputs.py
dremio/models/jobs.py
dremio/models/lineage.py
dremio/models/reflections.py
dremio/models/schema.py
dremio/models/unions.py
dremio/models/utils.py
dremio/utils/__init__.py
dremio/utils/converter.py
dremio/utils/decorators.py
dremio/utils/multithreading.py
dremio/utils/parser.py
dremio/utils/validation.py
pydremio-0.4.0.dist-info/METADATA
pydremio-0.4.0.dist-info/WHEEL
pydremio-0.4.0.dist-info/licenses/LICENSE.txt
pydremio-0.4.0.dist-info/RECORD
