Metadata-Version: 2.4
Name: pydremio
Version: 0.4.0
Summary: A Dremio SDK for interacting with one or more Dremio instances
Project-URL: Homepage, https://github.com/continental/pydremio
Project-URL: Issues, https://github.com/continental/pydremio/issues
Author-email: Holger Zernetsch <6146286+holgerzer@users.noreply.github.com>, Jan Pietsch <55839828+Piitschy@users.noreply.github.com>
License-File: LICENSE.txt
Classifier: Operating System :: OS Independent
Classifier: Programming Language :: Python :: 3
Requires-Python: >=3.12
Requires-Dist: certifi==2025.1.31
Requires-Dist: pandas==2.2.3
Requires-Dist: polars==1.23.0
Requires-Dist: prettytable==3.14.0
Requires-Dist: pyarrow==19.0.1
Requires-Dist: python-dotenv==1.0.1
Requires-Dist: requests==2.32.3
Requires-Dist: typing-extensions==4.12.2
Provides-Extra: build
Requires-Dist: build; extra == 'build'
Provides-Extra: test
Requires-Dist: pytest; extra == 'test'
Requires-Dist: testcontainers; extra == 'test'
